mcp_django_debug/__init__.py
mcp_django_debug-0.1.0a1.dist-info/WHEEL
mcp_django_debug-0.1.0a1.dist-info/METADATA
mcp_django_debug-0.1.0a1.dist-info/RECORD
