Metadata-Version: 2.3
Name: mcp-django-debug
Version: 0.1.0a1
Summary: MCP server for Django projects
Author: Josh Thomas
Author-email: Josh Thomas <josh@joshthomas.dev>
Classifier: Development Status :: 1 - Planning
Requires-Python: >=3.10
